{
  "id": "715a1dba-4e9f-4158-8346-3473b6e3557f",
  "name": "Mammoth",
  "market": "Utah",
  "alias": "UTA",
  "venue": {
    "id": "75d00a4f-d5de-4177-9de1-20469d18217b",
    "name": "Delta Center",
    "capacity": 18300,
    "address": "301 S Temple Street",
    "city": "Salt Lake City",
    "state": "UT",
    "zip": "84101",
    "country": "USA",
    "time_zone": "US/Mountain"
  },
  "league": {
    "id": "fd560107-a85b-4388-ab0d-655ad022aff7",
    "name": "NHL",
    "alias": "NHL"
  },
  "conference": {
    "id": "64901512-9ca9-4bea-aa80-16dbcbdae230",
    "name": "WESTERN CONFERENCE",
    "alias": "WESTERN"
  },
  "division": {
    "id": "5e868c4d-c6a3-4901-bc3c-3b7a4509e402",
    "name": "Central",
    "alias": "CENTRAL"
  },
  "coaches": [
    {
      "id": "80175e9f-18ab-4219-a90b-b79e322cc2ba",
      "full_name": "Andre Tourigny",
      "first_name": "Andre",
      "last_name": "Tourigny",
      "position": "Head Coach",
      "experience": "5"
    }
  ],
  "players": [
    {
      "id": "00cc69f0-afdf-4259-8712-2bcb6ca1d12f",
      "status": "ACT",
      "full_name": "Clayton Keller",
      "first_name": "Clayton",
      "last_name": "Keller",
      "abbr_name": "C.Keller",
      "height": 70,
      "weight": 175,
      "handedness": "L",
      "position": "F",
      "primary_position": "RW",
      "jersey_number": "9",
      "college": "Boston University",
      "experience": "9",
      "birth_place": "Chesterfield, MO, USA",
      "birthdate": "1998-07-29",
      "updated": "2025-11-20T22:10:36Z",
      "draft": {
        "team_id": "44153da1-0f24-11e2-8525-18a905767e44",
        "year": 2016,
        "round": "1",
        "pick": "7"
      }
    },
    {
      "id": "1f2d2adf-f492-4cad-b014-f464de855503",
      "status": "ACT",
      "full_name": "Michael Carcone",
      "first_name": "Michael",
      "last_name": "Carcone",
      "abbr_name": "M.Carcone",
      "height": 69,
      "weight": 182,
      "handedness": "L",
      "position": "F",
      "primary_position": "LW",
      "jersey_number": "53",
      "experience": "4",
      "birth_place": "Ajax, ON, CAN",
      "birthdate": "1996-05-19",
      "updated": "2025-09-18T22:58:12Z"
    },
    {
      "id": "24fbc040-3dcc-48b3-95c5-35fc8d03fb76",
      "status": "IR",
      "full_name": "Logan Cooley",
      "first_name": "Logan",
      "last_name": "Cooley",
      "abbr_name": "L.Cooley",
      "height": 72,
      "weight": 191,
      "handedness": "L",
      "position": "F",
      "primary_position": "C",
      "jersey_number": "92",
      "college": "Minnesota",
      "experience": "2",
      "birth_place": "Pittsburgh, PA, USA",
      "birthdate": "2004-05-04",
      "updated": "2025-12-13T16:18:35Z",
      "draft": {
        "team_id": "44153da1-0f24-11e2-8525-18a905767e44",
        "year": 2022,
        "round": "1",
        "pick": "3"
      },
      "injuries": [
        {
          "id": "4cf944fa-445b-4881-98eb-8aca7ad77efb",
          "status": "Out",
          "start_date": "2025-12-06",
          "update_date": "2025-12-13",
          "comment": "The Utah Mammoth placed F Logan Cooley on injured reserve on Saturday (Dec. 13).",
          "desc": "Lower Body"
        }
      ]
    },
    {
      "id": "2ab81af3-f54e-4968-90ef-a092a7400e79",
      "status": "ACT",
      "full_name": "Daniil But",
      "first_name": "Daniil",
      "last_name": "But",
      "abbr_name": "D.But",
      "height": 77,
      "weight": 203,
      "handedness": "R",
      "position": "F",
      "primary_position": "LW",
      "jersey_number": "19",
      "experience": "0",
      "birth_place": "Yaroslavl,, RUS",
      "birthdate": "2005-02-15",
      "updated": "2025-12-03T14:58:30Z",
      "draft": {
        "team_id": "44153da1-0f24-11e2-8525-18a905767e44",
        "year": 2023,
        "round": "1",
        "pick": "12"
      }
    },
    {
      "id": "35230501-c37d-4cf5-8412-ad682ecc3660",
      "status": "ACT",
      "full_name": "Nick DeSimone",
      "first_name": "Nick",
      "last_name": "DeSimone",
      "abbr_name": "N.DeSimone",
      "height": 74,
      "weight": 194,
      "handedness": "R",
      "position": "D",
      "primary_position": "D",
      "jersey_number": "57",
      "college": "Union (NY)",
      "experience": "3",
      "birth_place": "East Amherst, NY, USA",
      "birthdate": "1994-11-21",
      "updated": "2025-09-18T23:10:13Z"
    },
    {
      "id": "42d3de3b-0f24-11e2-8525-18a905767e44",
      "status": "ACT",
      "full_name": "Ian Cole",
      "first_name": "Ian",
      "last_name": "Cole",
      "abbr_name": "I.Cole",
      "height": 73,
      "weight": 237,
      "handedness": "L",
      "position": "D",
      "primary_position": "D",
      "jersey_number": "28",
      "college": "Notre Dame",
      "experience": "15",
      "birth_place": "Ann Arbor, MI, USA",
      "birthdate": "1989-02-21",
      "updated": "2025-09-18T23:09:44Z",
      "draft": {
        "team_id": "441660ea-0f24-11e2-8525-18a905767e44",
        "year": 2007,
        "round": "1",
        "pick": "18"
      }
    },
    {
      "id": "4436c7b3-4b38-4f13-ba0e-07d68fcb7056",
      "status": "ACT",
      "full_name": "Vitek Vanecek",
      "first_name": "Vitek",
      "last_name": "Vanecek",
      "abbr_name": "V.Vanecek",
      "height": 74,
      "weight": 184,
      "handedness": "L",
      "position": "G",
      "primary_position": "G",
      "jersey_number": "41",
      "experience": "5",
      "birth_place": "Havlickuv Brod,, CZE",
      "birthdate": "1996-01-09",
      "updated": "2025-09-18T23:45:19Z",
      "draft": {
        "team_id": "4417eede-0f24-11e2-8525-18a905767e44",
        "year": 2014,
        "round": "2",
        "pick": "39"
      }
    },
    {
      "id": "518be539-a589-49a9-a801-c1b360164d1d",
      "status": "ACT",
      "full_name": "Lawson Crouse",
      "first_name": "Lawson",
      "last_name": "Crouse",
      "abbr_name": "L.Crouse",
      "height": 76,
      "weight": 214,
      "handedness": "L",
      "position": "F",
      "primary_position": "LW",
      "jersey_number": "67",
      "experience": "9",
      "birth_place": "Mount Brydges, ON, CAN",
      "birthdate": "1997-06-23",
      "updated": "2025-09-18T22:58:37Z",
      "draft": {
        "team_id": "4418464d-0f24-11e2-8525-18a905767e44",
        "year": 2015,
        "round": "1",
        "pick": "11"
      }
    },
    {
      "id": "5c17a40f-bb24-40f5-910f-d8d487058e5b",
      "status": "ACT",
      "full_name": "Kevin Stenlund",
      "first_name": "Kevin",
      "last_name": "Stenlund",
      "abbr_name": "K.Stenlund",
      "height": 75,
      "weight": 213,
      "handedness": "R",
      "position": "F",
      "primary_position": "C",
      "jersey_number": "82",
      "experience": "7",
      "birth_place": "Stockholm,, SWE",
      "birthdate": "1996-09-20",
      "updated": "2025-09-18T23:08:34Z",
      "draft": {
        "team_id": "44167db4-0f24-11e2-8525-18a905767e44",
        "year": 2015,
        "round": "2",
        "pick": "58"
      }
    },
    {
      "id": "5c78e3bd-fa23-431c-b2d9-7d52a3be0c20",
      "status": "ACT",
      "full_name": "JJ Peterka",
      "first_name": "JJ",
      "last_name": "Peterka",
      "abbr_name": "J.Peterka",
      "height": 72,
      "weight": 189,
      "handedness": "L",
      "position": "F",
      "primary_position": "RW",
      "jersey_number": "77",
      "experience": "4",
      "birth_place": "Munich,, DEU",
      "birthdate": "2002-01-14",
      "updated": "2025-09-18T23:07:55Z",
      "draft": {
        "team_id": "4416d559-0f24-11e2-8525-18a905767e44",
        "year": 2020,
        "round": "2",
        "pick": "34"
      }
    },
    {
      "id": "64263c1b-e34e-410e-a212-5ec20e24d361",
      "status": "ACT",
      "full_name": "Olli Maatta",
      "first_name": "Olli",
      "last_name": "Maatta",
      "abbr_name": "O.Maatta",
      "height": 74,
      "weight": 207,
      "handedness": "L",
      "position": "D",
      "primary_position": "D",
      "jersey_number": "2",
      "experience": "12",
      "birth_place": "Jyvaskyla,, FIN",
      "birthdate": "1994-08-22",
      "updated": "2025-12-12T20:35:33Z",
      "draft": {
        "team_id": "4417b7d7-0f24-11e2-8525-18a905767e44",
        "year": 2012,
        "round": "1",
        "pick": "22"
      }
    },
    {
      "id": "6a4577cd-013b-4d4c-b35a-87f581a0f98e",
      "status": "ACT",
      "full_name": "Liam O'Brien",
      "first_name": "Liam",
      "last_name": "O'Brien",
      "abbr_name": "L.O'Brien",
      "height": 73,
      "weight": 215,
      "handedness": "L",
      "position": "F",
      "primary_position": "C",
      "jersey_number": "38",
      "experience": "8",
      "birth_place": "Halifax, NS, CAN",
      "birthdate": "1994-07-29",
      "updated": "2025-10-17T18:56:19Z"
    },
    {
      "id": "6d438214-071b-4759-9191-dffcffc318b7",
      "status": "ACT",
      "full_name": "Alexander Kerfoot",
      "first_name": "Alexander",
      "last_name": "Kerfoot",
      "abbr_name": "A.Kerfoot",
      "height": 71,
      "weight": 185,
      "handedness": "L",
      "position": "F",
      "primary_position": "C",
      "jersey_number": "15",
      "college": "Harvard",
      "experience": "8",
      "birth_place": "Vancouver, BC, CAN",
      "birthdate": "1994-08-11",
      "updated": "2025-12-20T02:11:04Z",
      "draft": {
        "team_id": "44174b0c-0f24-11e2-8525-18a905767e44",
        "year": 2012,
        "round": "5",
        "pick": "150"
      }
    },
    {
      "id": "78e9f6dd-2ef8-458e-8363-731b2d520e62",
      "status": "ACT",
      "full_name": "John Marino",
      "first_name": "John",
      "last_name": "Marino",
      "abbr_name": "J.Marino",
      "height": 73,
      "weight": 200,
      "handedness": "R",
      "position": "D",
      "primary_position": "D",
      "jersey_number": "6",
      "college": "Harvard",
      "experience": "6",
      "birth_place": "North Easton, MA, USA",
      "birthdate": "1997-05-21",
      "updated": "2025-10-28T22:28:49Z",
      "draft": {
        "team_id": "4415ea6c-0f24-11e2-8525-18a905767e44",
        "year": 2015,
        "round": "6",
        "pick": "154"
      }
    },
    {
      "id": "8b968705-833a-4251-92d7-eef4c0721953",
      "status": "ACT",
      "full_name": "Kailer Yamamoto",
      "first_name": "Kailer",
      "last_name": "Yamamoto",
      "abbr_name": "K.Yamamoto",
      "height": 69,
      "weight": 178,
      "handedness": "R",
      "position": "F",
      "primary_position": "RW",
      "jersey_number": "56",
      "experience": "8",
      "birth_place": "Spokane, WA, USA",
      "birthdate": "1998-09-29",
      "updated": "2025-10-12T19:38:46Z",
      "draft": {
        "team_id": "4415ea6c-0f24-11e2-8525-18a905767e44",
        "year": 2017,
        "round": "1",
        "pick": "22"
      }
    },
    {
      "id": "8bfb6025-5aae-4654-8a67-d836b2739283",
      "status": "ACT",
      "full_name": "Nick Schmaltz",
      "first_name": "Nick",
      "last_name": "Schmaltz",
      "abbr_name": "N.Schmaltz",
      "height": 72,
      "weight": 184,
      "handedness": "R",
      "position": "F",
      "primary_position": "C",
      "jersey_number": "8",
      "college": "North Dakota",
      "experience": "9",
      "birth_place": "Madison, WI, USA",
      "birthdate": "1996-02-23",
      "updated": "2025-09-18T23:08:12Z",
      "draft": {
        "team_id": "4416272f-0f24-11e2-8525-18a905767e44",
        "year": 2014,
        "round": "1",
        "pick": "20"
      }
    },
    {
      "id": "a6c0a0de-646d-42b6-8684-9ca21070476b",
      "status": "ACT",
      "full_name": "Sean Durzi",
      "first_name": "Sean",
      "last_name": "Durzi",
      "abbr_name": "S.Durzi",
      "height": 73,
      "weight": 196,
      "handedness": "R",
      "position": "D",
      "primary_position": "D",
      "jersey_number": "50",
      "experience": "4",
      "birth_place": "Mississauga, ON, CAN",
      "birthdate": "1998-10-21",
      "updated": "2025-11-26T19:51:55Z",
      "draft": {
        "team_id": "441730a9-0f24-11e2-8525-18a905767e44",
        "year": 2018,
        "round": "2",
        "pick": "52"
      }
    },
    {
      "id": "a82f9092-8190-45da-aba6-0d19cad1ed83",
      "status": "ACT",
      "full_name": "Mikhail Sergachev",
      "first_name": "Mikhail",
      "last_name": "Sergachev",
      "abbr_name": "M.Sergachev",
      "height": 75,
      "weight": 212,
      "handedness": "L",
      "position": "D",
      "primary_position": "D",
      "jersey_number": "98",
      "experience": "9",
      "birth_place": "Nizhnekamsk,, RUS",
      "birthdate": "1998-06-25",
      "updated": "2025-09-18T23:41:48Z",
      "draft": {
        "team_id": "441713b7-0f24-11e2-8525-18a905767e44",
        "year": 2016,
        "round": "1",
        "pick": "9"
      }
    },
    {
      "id": "a9695f86-c215-4d21-95b3-005aef49ad0c",
      "status": "ACT",
      "full_name": "Dylan Guenther",
      "first_name": "Dylan",
      "last_name": "Guenther",
      "abbr_name": "D.Guenther",
      "height": 73,
      "weight": 191,
      "handedness": "R",
      "position": "F",
      "primary_position": "RW",
      "jersey_number": "11",
      "experience": "3",
      "birth_place": "Edmonton, AB, CAN",
      "birthdate": "2003-04-10",
      "updated": "2025-09-18T23:01:24Z",
      "draft": {
        "team_id": "44153da1-0f24-11e2-8525-18a905767e44",
        "year": 2021,
        "round": "1",
        "pick": "9"
      }
    },
    {
      "id": "bf30bab4-e024-4038-9fa6-532023216934",
      "status": "ACT",
      "full_name": "Barrett Hayton",
      "first_name": "Barrett",
      "last_name": "Hayton",
      "abbr_name": "B.Hayton",
      "height": 73,
      "weight": 200,
      "handedness": "L",
      "position": "F",
      "primary_position": "C",
      "jersey_number": "27",
      "experience": "6",
      "birth_place": "Peterborough, ON, CAN",
      "birthdate": "2000-06-09",
      "updated": "2025-09-18T23:02:25Z",
      "draft": {
        "team_id": "44153da1-0f24-11e2-8525-18a905767e44",
        "year": 2018,
        "round": "1",
        "pick": "5"
      }
    },
    {
      "id": "cb2d1eb9-ed27-4fff-96ea-8e82d9dcff64",
      "status": "ACT",
      "full_name": "Brandon Tanev",
      "first_name": "Brandon",
      "last_name": "Tanev",
      "abbr_name": "B.Tanev",
      "height": 72,
      "weight": 189,
      "handedness": "L",
      "position": "F",
      "primary_position": "LW",
      "jersey_number": "13",
      "college": "Providence",
      "experience": "10",
      "birth_place": "Toronto, ON, CAN",
      "birthdate": "1991-12-31",
      "updated": "2025-09-18T23:08:43Z"
    },
    {
      "id": "d8099c30-1c1e-4c66-abbd-7d9de11ba05f",
      "status": "ACT",
      "full_name": "Karel Vejmelka",
      "first_name": "Karel",
      "last_name": "Vejmelka",
      "abbr_name": "K.Vejmelka",
      "height": 76,
      "weight": 221,
      "handedness": "R",
      "position": "G",
      "primary_position": "G",
      "jersey_number": "70",
      "experience": "4",
      "birth_place": "Trebic,, CZE",
      "birthdate": "1996-05-25",
      "updated": "2026-01-01T19:33:03Z",
      "draft": {
        "team_id": "441643b7-0f24-11e2-8525-18a905767e44",
        "year": 2015,
        "round": "5",
        "pick": "145"
      }
    },
    {
      "id": "e6fc4e06-9c16-11e2-a01b-f4ce4684ea4c",
      "status": "ACT",
      "full_name": "Nate Schmidt",
      "first_name": "Nate",
      "last_name": "Schmidt",
      "abbr_name": "N.Schmidt",
      "height": 72,
      "weight": 197,
      "handedness": "L",
      "position": "D",
      "primary_position": "D",
      "jersey_number": "88",
      "college": "Minnesota",
      "experience": "12",
      "birth_place": "St. Cloud, MN, USA",
      "birthdate": "1991-07-16",
      "updated": "2025-09-18T23:41:36Z"
    },
    {
      "id": "f09e6fc9-c037-4985-a9e2-9146e61eeecb",
      "status": "ACT",
      "full_name": "Jack McBain",
      "first_name": "Jack",
      "last_name": "McBain",
      "abbr_name": "J.McBain",
      "height": 76,
      "weight": 219,
      "handedness": "L",
      "position": "F",
      "primary_position": "C",
      "jersey_number": "22",
      "college": "Boston College",
      "experience": "4",
      "birth_place": "Toronto, ON, CAN",
      "birthdate": "2000-01-06",
      "updated": "2025-09-18T23:06:33Z",
      "draft": {
        "team_id": "4416091c-0f24-11e2-8525-18a905767e44",
        "year": 2018,
        "round": "3",
        "pick": "63"
      }
    }
  ]
}